MuyGPyS/__init__.py
MuyGPyS/neighbors.py
MuyGPyS/utils.py
MuyGPyS/examples/__init__.py
MuyGPyS/examples/classify.py
MuyGPyS/examples/regress.py
MuyGPyS/examples/two_class_classify_uq.py
MuyGPyS/gp/__init__.py
MuyGPyS/gp/distance.py
MuyGPyS/gp/kernels.py
MuyGPyS/gp/muygps.py
MuyGPyS/optimize/__init__.py
MuyGPyS/optimize/batch.py
MuyGPyS/optimize/chassis.py
MuyGPyS/optimize/objective.py
MuyGPyS/testing/__init__.py
MuyGPyS/testing/api_tests.py
MuyGPyS/testing/gp.py
MuyGPyS/testing/test_utils.py
muygps-0.3.0.dist-info/LICENSE-MIT
muygps-0.3.0.dist-info/METADATA
muygps-0.3.0.dist-info/NOTICE
muygps-0.3.0.dist-info/WHEEL
muygps-0.3.0.dist-info/top_level.txt
muygps-0.3.0.dist-info/RECORD
