Metadata-Version: 2.1
Name: muygps
Version: 0.3.0
Summary: Scalable Approximate Gaussian Process using Local Kriging
Home-page: https://github.com/LLNL/MuyGPyS
Author: Benjamin W. Priest
Author-email: priest2@llnl.gov
License: MIT
Download-URL: https://pypi.org/project/muygpys
Project-URL: Source Code, https://github.com/LLNL/MuyGPyS
Project-URL: Documentation, https://muygpys.readthedocs.io
Project-URL: Bug Tracker, https://github.com/LLNL/MuyGPyS/issues
Platform: UNKNOWN
Classifier: Programming Language :: Python :: 3.6
Classifier: Programming Language :: Python :: 3.7
Classifier: Programming Language :: Python :: 3.8
Classifier: Programming Language :: Python :: 3.9
Classifier: License :: OSI Approved :: MIT License
Classifier: Operating System :: MacOS
Classifier: Operating System :: POSIX :: Linux
Classifier: Topic :: Software Development
Classifier: Topic :: Software Development :: Libraries
Classifier: Topic :: Software Development :: Libraries :: Python Modules
Classifier: Topic :: Scientific/Engineering
Classifier: Topic :: Scientific/Engineering :: Mathematics
Classifier: Topic :: Scientific/Engineering
Classifier: Intended Audience :: Science/Research
Classifier: Intended Audience :: Developers
Classifier: Intended Audience :: Education
Classifier: Development Status :: 3 - Alpha
Requires-Python: >=3.6
License-File: LICENSE-MIT
License-File: NOTICE
Requires-Dist: numpy (>=1.18.5)
Requires-Dist: scipy (==1.4.1)
Requires-Dist: scikit-learn (>=0.23.2)
Requires-Dist: absl-py (>=0.13.0)
Requires-Dist: pybind11 (>=2.5.0)
Requires-Dist: hnswlib (>=0.5.2)
